{"namedChunkGroups":{"polyfill":{"name":"polyfill","assets":[{"name":"webpack-runtime-51324e374ed37465ff51.js","size":5346},{"name":"polyfill-8eb7433d0cb153530031.js","size":82517}],"filteredAssets":0,"assetsSize":87863,"filteredAuxiliaryAssets":2,"auxiliaryAssetsSize":221582},"app":{"name":"app","assets":[{"name":"webpack-runtime-51324e374ed37465ff51.js","size":5346},{"name":"framework-c49643cdc45c711b03f2.js","size":128985},{"name":"app-953c4c1fb7f87c761f6c.js","size":68811}],"filteredAssets":0,"assetsSize":203142,"filteredAuxiliaryAssets":3,"auxiliaryAssetsSize":653419},"component---src-pages-404-js":{"name":"component---src-pages-404-js","assets":[{"name":"styles.4ec8c64d1a58aa5f0400.css","size":6994},{"name":"commons-dc2181617392bfe3b009.js","size":17090},{"name":"component---src-pages-404-js-fef27fb824ef293c36bf.js","size":505}],"filteredAssets":0,"assetsSize":24589,"filteredAuxiliaryAssets":2,"auxiliaryAssetsSize":71479},"component---src-pages-about-js":{"name":"component---src-pages-about-js","assets":[{"name":"styles.4ec8c64d1a58aa5f0400.css","size":6994},{"name":"commons-dc2181617392bfe3b009.js","size":17090},{"name":"component---src-pages-about-js-d44db0bdebf35c815ad9.js","size":439}],"filteredAssets":0,"assetsSize":24523,"filteredAuxiliaryAssets":2,"auxiliaryAssetsSize":71324},"component---src-pages-contact-js":{"name":"component---src-pages-contact-js","assets":[{"name":"styles.4ec8c64d1a58aa5f0400.css","size":6994},{"name":"commons-dc2181617392bfe3b009.js","size":17090},{"name":"component---src-pages-contact-js-16c806ae4bf06d040fb0.js","size":1155}],"filteredAssets":0,"assetsSize":25239,"filteredAuxiliaryAssets":2,"auxiliaryAssetsSize":72844},"component---src-pages-index-js":{"name":"component---src-pages-index-js","assets":[{"name":"styles.4ec8c64d1a58aa5f0400.css","size":6994},{"name":"commons-dc2181617392bfe3b009.js","size":17090},{"name":"component---src-pages-index-js-94d8f54314b28247fabb.js","size":20244}],"filteredAssets":0,"assetsSize":44328,"filteredAuxiliaryAssets":2,"auxiliaryAssetsSize":108909},"component---src-pages-projects-js":{"name":"component---src-pages-projects-js","assets":[{"name":"styles.4ec8c64d1a58aa5f0400.css","size":6994},{"name":"commons-dc2181617392bfe3b009.js","size":17090},{"name":"8e92b07c528ccb1dd4cf5c41d548054d52ab265f-617767b1c7366699b255.js","size":10582},{"name":"component---src-pages-projects-js-a948744e60ca12761299.js","size":835}],"filteredAssets":0,"assetsSize":35501,"filteredAuxiliaryAssets":3,"auxiliaryAssetsSize":115616},"component---src-pages-thanks-js":{"name":"component---src-pages-thanks-js","assets":[{"name":"styles.4ec8c64d1a58aa5f0400.css","size":6994},{"name":"commons-dc2181617392bfe3b009.js","size":17090},{"name":"component---src-pages-thanks-js-b32ff3fd73df3ec7adb9.js","size":1775}],"filteredAssets":0,"assetsSize":25859,"filteredAuxiliaryAssets":2,"auxiliaryAssetsSize":73173},"component---src-templates-project-js":{"name":"component---src-templates-project-js","assets":[{"name":"styles.4ec8c64d1a58aa5f0400.css","size":6994},{"name":"commons-dc2181617392bfe3b009.js","size":17090},{"name":"8e92b07c528ccb1dd4cf5c41d548054d52ab265f-617767b1c7366699b255.js","size":10582},{"name":"component---src-templates-project-js-73d479d870e389b5c9e7.js","size":13335}],"filteredAssets":0,"assetsSize":48001,"filteredAuxiliaryAssets":3,"auxiliaryAssetsSize":175354}},"assetsByChunkName":{"polyfill":["webpack-runtime-51324e374ed37465ff51.js","polyfill-8eb7433d0cb153530031.js"],"app":["webpack-runtime-51324e374ed37465ff51.js","framework-c49643cdc45c711b03f2.js","app-953c4c1fb7f87c761f6c.js"],"component---src-pages-404-js":["styles.4ec8c64d1a58aa5f0400.css","commons-dc2181617392bfe3b009.js","component---src-pages-404-js-fef27fb824ef293c36bf.js"],"component---src-pages-about-js":["styles.4ec8c64d1a58aa5f0400.css","commons-dc2181617392bfe3b009.js","component---src-pages-about-js-d44db0bdebf35c815ad9.js"],"component---src-pages-contact-js":["styles.4ec8c64d1a58aa5f0400.css","commons-dc2181617392bfe3b009.js","component---src-pages-contact-js-16c806ae4bf06d040fb0.js"],"component---src-pages-index-js":["styles.4ec8c64d1a58aa5f0400.css","commons-dc2181617392bfe3b009.js","component---src-pages-index-js-94d8f54314b28247fabb.js"],"component---src-pages-projects-js":["styles.4ec8c64d1a58aa5f0400.css","commons-dc2181617392bfe3b009.js","8e92b07c528ccb1dd4cf5c41d548054d52ab265f-617767b1c7366699b255.js","component---src-pages-projects-js-a948744e60ca12761299.js"],"component---src-pages-thanks-js":["styles.4ec8c64d1a58aa5f0400.css","commons-dc2181617392bfe3b009.js","component---src-pages-thanks-js-b32ff3fd73df3ec7adb9.js"],"component---src-templates-project-js":["styles.4ec8c64d1a58aa5f0400.css","commons-dc2181617392bfe3b009.js","8e92b07c528ccb1dd4cf5c41d548054d52ab265f-617767b1c7366699b255.js","component---src-templates-project-js-73d479d870e389b5c9e7.js"]},"childAssetsByChunkName":{}}